[
  {
    "Nombre": "Abril Club De Campo",
    "Dirección": "Autopista Bs. As.- La Plata Km. 30,5",
    "Localidad": "Berazategui",
    "Código Postal": "1884",
    "Teléfono": "4215-4000  4215-2136  4342-6618/6620",
    "maps_url": "",
    "rating": ""
  },
  {
    "Nombre": "Aero Club Fortin Lobos",
    "Dirección": "Ruta Nac. Nº 205 Km. 106",
    "Localidad": "Lobos",
    "Código Postal": "7240",
    "Teléfono": "02227-421700/494496",
    "maps_url": "https://maps.google.com/?cid=2640171560898262574",
    "rating": 4.7
  },
  {
    "Nombre": "Aero Golf Club De Coronel Suarez",
    "Dirección": "Av. Mateo Llovera S/Nº Seccion Quintas",
    "Localidad": "Coronel Suarez",
    "Código Postal": "7540",
    "Teléfono": "02926 - 431811 / 422196",
    "maps_url": "https://maps.google.com/?cid=832573063813836832",
    "rating": 4.5
  },
  {
    "Nombre": "Aranjuez Country Club",
    "Dirección": "Ruta 9 Km. 47",
    "Localidad": "Escobar",
    "Código Postal": "1625",
    "Teléfono": "03488-424202",
    "maps_url": "",
    "rating": ""
  },
  {
    "Nombre": "Aranzazu Club De Campo",
    "Dirección": "Panam. Ramal Pilar Hasta Garin",
    "Localidad": "Garin",
    "Código Postal": "1619",
    "Teléfono": "03327-456575/76",
    "maps_url": "https://maps.google.com/?cid=15904918844623828503",
    "rating": 4.4
  },
  {
    "Nombre": "Area 60 Golf Club",
    "Dirección": "Casilla De Correo 9",
    "Localidad": "Brandsen",
    "Código Postal": "1980",
    "Teléfono": "0800 - 4440607",
    "maps_url": "https://maps.google.com/?cid=7239322838558021837",
    "rating": 4.8
  },
  {
    "Nombre": "Areco Golf S.A.",
    "Dirección": "Ruta 8 Y 41",
    "Localidad": "San Antonio De Areco",
    "Código Postal": "2760",
    "Teléfono": "02326-453073",
    "maps_url": "",
    "rating": ""
  },
  {
    "Nombre": "Asociacion Civil G. C. Bco. Provincia",
    "Dirección": "Almafuerte Y Gorriti",
    "Localidad": "Fco. Alvarez (Moreno)",
    "Código Postal": "1746",
    "Teléfono": "0237-4830865 FAX 4830779",
    "maps_url": "https://maps.google.com/?cid=2385680614479118983",
    "rating": 2.4
  },
  {
    "Nombre": "Asociacion Civil Hurlingham Club",
    "Dirección": "Av. Julio Argentino Roca 1411",
    "Localidad": "Hurlingham",
    "Código Postal": "1686",
    "Teléfono": "4662-5510/4 FAX 4662-5516",
    "maps_url": "https://maps.google.com/?cid=14251360479633531605",
    "rating": 4.5
  },
  {
    "Nombre": "Boca Raton Country Life S.A.",
    "Dirección": "Ruta 25 Km. 12",
    "Localidad": "Pilar",
    "Código Postal": "1629",
    "Teléfono": "02304-457129 (Of.Golf ) 11-3729-4279 (Starter)",
    "maps_url": "",
    "rating": ""
  },
  {
    "Nombre": "Bolivar Golf Club",
    "Dirección": "Alte. Brown 255",
    "Localidad": "San Carlos Bolivar",
    "Código Postal": "6550",
    "Teléfono": "02314 - 424504 / 428882 / 420929",
    "maps_url": "https://maps.google.com/?cid=2998910483296756241",
    "rating": 4.3
  },
  {
    "Nombre": "Boulogne Golf Club",
    "Dirección": "Ruta Panam. Y Camino Real Moron",
    "Localidad": "Boulogne",
    "Código Postal": "1609",
    "Teléfono": "4765-7525/7508",
    "maps_url": "https://maps.google.com/?cid=4708751618339714205",
    "rating": 4.3
  },
  {
    "Nombre": "Bragado Golf Club",
    "Dirección": "Cuartel Iii Pdo. Bragado",
    "Localidad": "Bragado",
    "Código Postal": "6640",
    "Teléfono": "02342-421341-1",
    "maps_url": "https://maps.google.com/?cid=3093311503768219192",
    "rating": 4.5
  },
  {
    "Nombre": "Buenos Aires Golf Club",
    "Dirección": "Mayor Irusta 3777",
    "Localidad": "Bella Vista",
    "Código Postal": "1661",
    "Teléfono": "4468 - 1737/2533/2036/1693",
    "maps_url": "https://maps.google.com/?cid=13388186016124157735",
    "rating": 4.4
  },
  {
    "Nombre": "Campo Chico Country Club",
    "Dirección": "Alborada S/Nº",
    "Localidad": "Matheu",
    "Código Postal": "1627",
    "Teléfono": "0348-4469400 (líneas rotativas)",
    "maps_url": "https://maps.google.com/?cid=7052957975446516693",
    "rating": 4.5
  },
  {
    "Nombre": "Campo De Golf La Orquidea",
    "Dirección": "600 M. De Ruta 6 Cno.Cap. Del Señor",
    "Localidad": "Los Cardales",
    "Código Postal": "2814",
    "Teléfono": "02322-493537",
    "maps_url": "",
    "rating": ""
  },
  {
    "Nombre": "Campo De Golf Los Alamos",
    "Dirección": "Calle Saravi S/Nº",
    "Localidad": "Pilar",
    "Código Postal": "1629",
    "Teléfono": "02304-472845/470277/470337",
    "maps_url": "https://maps.google.com/?cid=15440330269457603330",
    "rating": 4.3
  },
  {
    "Nombre": "Campo Grande Club De Campo",
    "Dirección": "Matacos Y Alborada S/N - Villa Rosa",
    "Localidad": "Pilar",
    "Código Postal": "1631",
    "Teléfono": "",
    "maps_url": "https://maps.google.com/?cid=8441342686280885813",
    "rating": 4.5
  },
  {
    "Nombre": "Cañuelas Golf",
    "Dirección": "Ruta 205 Km. 67,5",
    "Localidad": "Cañuelas",
    "Código Postal": "1814",
    "Teléfono": "02226 - 433200",
    "maps_url": "",
    "rating": ""
  },
  {
    "Nombre": "Carilo Golf Club",
    "Dirección": "Ñandu Y Perdiz",
    "Localidad": "Pque. Carilo Pinamar",
    "Código Postal": "7167",
    "Teléfono": "02254-470044 / 570044",
    "maps_url": "https://maps.google.com/?cid=8282568277444133490",
    "rating": 4.5
  },
  {
    "Nombre": "Carmel Country Club",
    "Dirección": "Monseñor De Andrea 1891",
    "Localidad": "Pilar",
    "Código Postal": "1629",
    "Teléfono": "02304 - 428709/663900",
    "maps_url": "https://maps.google.com/?cid=3870647590856312371",
    "rating": 4.4
  },
  {
    "Nombre": "Chacabuco Golf Club",
    "Dirección": "Ruta Nac. Nº 7 Km. 198",
    "Localidad": "Chacabuco",
    "Código Postal": "6740",
    "Teléfono": "02352-427112 / 427700",
    "maps_url": "https://maps.google.com/?cid=13047546681664677831",
    "rating": 4.6
  },
  {
    "Nombre": "Chacras Del Parana Club De Campo",
    "Dirección": "Camino A Baradero S/N° Km. 107",
    "Localidad": "Zarate",
    "Código Postal": "2800",
    "Teléfono": "4328 - 7555",
    "maps_url": "",
    "rating": ""
  },
  {
    "Nombre": "Circulo De La Fuerza Aerea",
    "Dirección": "Campo Cabeza De Caballo",
    "Localidad": "Ezeiza",
    "Código Postal": "1804",
    "Teléfono": "4234-1263",
    "maps_url": "https://maps.google.com/?cid=18319357154428162675",
    "rating": 4.4
  },
  {
    "Nombre": "Club At. Bco. Provincia De Bs. As.",
    "Dirección": "Acceso Oeste Km. 44/45",
    "Localidad": "Francisco Alvarez",
    "Código Postal": "1746",
    "Teléfono": "4791-0832 0237-4830437/9",
    "maps_url": "https://maps.google.com/?cid=13216185880828125724",
    "rating": 4.3
  },
  {
    "Nombre": "Club At. Estudiantes De La Plata",
    "Dirección": "Calle 9 Y 135",
    "Localidad": "City Bell",
    "Código Postal": "1896",
    "Teléfono": "0221-4752754",
    "maps_url": "https://maps.google.com/?cid=12925879861303403374",
    "rating": 4.6
  },
  {
    "Nombre": "Club At. Estudiantes De Olavarria",
    "Dirección": "Lavalle Y Cortes",
    "Localidad": "Olavarria",
    "Código Postal": "7400",
    "Teléfono": "02284-427334",
    "maps_url": "https://maps.google.com/?cid=17548380306802709128",
    "rating": 4.6
  },
  {
    "Nombre": "Club Atletico 9 De Julio",
    "Dirección": "Av. Benedetti 274",
    "Localidad": "9 De Julio",
    "Código Postal": "6500",
    "Teléfono": "02317-422378 02345",
    "maps_url": "https://maps.google.com/?cid=12692315371544649549",
    "rating": 4.5
  },
  {
    "Nombre": "Club Atletico De San Isidro",
    "Dirección": "Italia S/N° Barrio San Isidro Labrador",
    "Localidad": "Benavidez",
    "Código Postal": "1621",
    "Teléfono": "4743 - 4242 / 0168",
    "maps_url": "https://maps.google.com/?cid=12066994164902282186",
    "rating": 4
  },
  {
    "Nombre": "Club Atletico Lomas",
    "Dirección": "Ruta 205 Km. 36,500 Parada Union Ferroviaria",
    "Localidad": "Ezeiza",
    "Código Postal": "1804",
    "Teléfono": "4234-8043 FAX 4244-0155",
    "maps_url": "https://maps.google.com/?cid=11665913681644892387",
    "rating": 4.5
  },
  {
    "Nombre": "Club C. De G. Las Praderas De Lujan",
    "Dirección": "Ruta 192 Km. 6,500",
    "Localidad": "Lujan",
    "Código Postal": "6700",
    "Teléfono": "02323-496209/12",
    "maps_url": "https://maps.google.com/?cid=9763951989241477426",
    "rating": 4.6
  },
  {
    "Nombre": "Club Cerro Pampa",
    "Dirección": "Cuartel Ix",
    "Localidad": "Tandil",
    "Código Postal": "7000",
    "Teléfono": "02293-420065",
    "maps_url": "https://maps.google.com/?cid=3410193061584179142",
    "rating": 4.9
  },
  {
    "Nombre": "Club De Campo Armenia",
    "Dirección": "Las Campanillas 602 Y Camelia",
    "Localidad": "Del Viso",
    "Código Postal": "1669",
    "Teléfono": "02320 - 470176",
    "maps_url": "https://maps.google.com/?cid=8163068302177332448",
    "rating": 4.4
  },
  {
    "Nombre": "Club De Campo El Moro",
    "Dirección": "Ruta 200 Km. 52,500",
    "Localidad": "Marcoz Paz",
    "Código Postal": "1717",
    "Teléfono": "0220-4770918/4771643",
    "maps_url": "https://maps.google.com/?cid=4631423688016768720",
    "rating": 4.5
  },
  {
    "Nombre": "Club De Campo Grand Bell",
    "Dirección": "Calle 467 Entre 142 Y 148",
    "Localidad": "City Bell",
    "Código Postal": "1896",
    "Teléfono": "0221-4750404 / 4750303",
    "maps_url": "https://maps.google.com/?cid=18294759196348163819",
    "rating": 4.3
  },
  {
    "Nombre": "Club De Campo Haras Del Sur",
    "Dirección": "Ruta 2 Km. 69",
    "Localidad": "La Plata",
    "Código Postal": "1900",
    "Teléfono": "02223 - 498765",
    "maps_url": "",
    "rating": ""
  },
  {
    "Nombre": "Club De Campo La Martona",
    "Dirección": "Ruta 205 Km. 54",
    "Localidad": "Vicente Casares",
    "Código Postal": "1808",
    "Teléfono": "02226-491240/280/290/596/504",
    "maps_url": "",
    "rating": ""
  },
  {
    "Nombre": "Club De Campo La Tradicion",
    "Dirección": "La Prensa Y Miro",
    "Localidad": "Francisco Alvarez",
    "Código Postal": "1746",
    "Teléfono": "011 - 62403211/13 0237 - 4873774",
    "maps_url": "https://maps.google.com/?cid=18255892233710729080",
    "rating": 4.5
  },
  {
    "Nombre": "Club De Campo Las Perdices",
    "Dirección": "Ruta Nac. N° 3 Km. 47,200",
    "Localidad": "Virrey Del Pino",
    "Código Postal": "1763",
    "Teléfono": "4382 - 0153 / 3204",
    "maps_url": "https://maps.google.com/?cid=16275438533307442613",
    "rating": 4.7
  },
  {
    "Nombre": "Club De Campo Los Horneros",
    "Dirección": "La Pista Y Caseros",
    "Localidad": "Ingeniero Maschwitz",
    "Código Postal": "1623",
    "Teléfono": "03484-486173/74",
    "maps_url": "https://maps.google.com/?cid=17726657080866594749",
    "rating": 4.4
  },
  {
    "Nombre": "Club De Campo Los Pingüinos",
    "Dirección": "Av. Pte. Peron 10298",
    "Localidad": "Ituzaingo",
    "Código Postal": "1714",
    "Teléfono": "4621-4716/4728/0064/0109",
    "maps_url": "https://maps.google.com/?cid=5265926690788628824",
    "rating": 4.5
  },
  {
    "Nombre": "Club De Campo Santana",
    "Dirección": "Ruta 73 S/Nro.",
    "Localidad": "Claromeco",
    "Código Postal": "7505",
    "Teléfono": "02983-430638/431820",
    "maps_url": "https://maps.google.com/?cid=18442713473827855463",
    "rating": 4.5
  },
  {
    "Nombre": "Club De Campo St.Thomas",
    "Dirección": "Ruta 52 Km 3,500",
    "Localidad": "Canning",
    "Código Postal": "1807",
    "Teléfono": "4295-8562/9384/9385",
    "maps_url": "https://maps.google.com/?cid=18005754740025080171",
    "rating": 4.7
  },
  {
    "Nombre": "Club De Golf Palihue",
    "Dirección": "Jacksonville 2",
    "Localidad": "Bahia Blanca",
    "Código Postal": "8000",
    "Teléfono": "0291-4524514/4543742",
    "maps_url": "https://maps.google.com/?cid=4615835747452069747",
    "rating": 4.3
  },
  {
    "Nombre": "Club De Pelota De Cnel. Pringles",
    "Dirección": "Boulevard S/Nº Y Ruta 51",
    "Localidad": "Coronel Pringles",
    "Código Postal": "7530",
    "Teléfono": "02922-464540/462325/462103",
    "maps_url": "https://maps.google.com/?cid=13279416950380051160",
    "rating": 4.5
  },
  {
    "Nombre": "Club Ferrocarril Mitre D. S. Y C.",
    "Dirección": "Colectora Gral. Paz 2702 Y Vias F.C.B.G.Mitre",
    "Localidad": "Miguelete (San  Martin)",
    "Código Postal": "1650",
    "Teléfono": "4752-9388 FAX 4713-3845",
    "maps_url": "https://maps.google.com/?cid=2443531834734279811",
    "rating": 4.4
  },
  {
    "Nombre": "Club Hipico Y De Golf City Bell",
    "Dirección": "Labougle Y 10",
    "Localidad": "City Bell",
    "Código Postal": "1896",
    "Teléfono": "0221-4800169",
    "maps_url": "https://maps.google.com/?cid=10681437935271007443",
    "rating": 4.4
  },
  {
    "Nombre": "Club Mar Del Plata S.A.",
    "Dirección": "Calles 24 Y 35",
    "Localidad": "Mar Del Plata",
    "Código Postal": "7600",
    "Teléfono": "0223-4672500 / 4672087",
    "maps_url": "https://maps.google.com/?cid=11296916384606149240",
    "rating": 4
  },
  {
    "Nombre": "Club Mun. De Golf Fortin Tordillo",
    "Dirección": "Paraje Colonia Fortin Tordillo",
    "Localidad": "Daireaux",
    "Código Postal": "6555",
    "Teléfono": "02316-454024/454145",
    "maps_url": "https://maps.google.com/?cid=937937165659439287",
    "rating": 4.6
  },
  {
    "Nombre": "Club Nautico Hacoaj",
    "Dirección": "Ruta 27 Y Galileo Galilei",
    "Localidad": "Tigre",
    "Código Postal": "1648",
    "Teléfono": "11 6972-2060",
    "maps_url": "https://maps.google.com/?cid=5808995342078115299",
    "rating": 4.4
  },
  {
    "Nombre": "Club Nautico San Isidro",
    "Dirección": "Av. Mitre 1999",
    "Localidad": "San Isidro",
    "Código Postal": "1642",
    "Teléfono": "4732-0600 FAX 4732-0440",
    "maps_url": "https://maps.google.com/?cid=4389174234146050206",
    "rating": 4.7
  },
  {
    "Nombre": "Club Newman",
    "Dirección": "Av De Los Constituyentes 7245",
    "Localidad": "Benavidez",
    "Código Postal": "1621",
    "Teléfono": "03327-481056/81296 322-9073 FAX 481312",
    "maps_url": "https://maps.google.com/?cid=16790164627367500518",
    "rating": 4.3
  },
  {
    "Nombre": "Club Privado El Ombu",
    "Dirección": "Blas Parera S/Nº",
    "Localidad": "Tristan Suarez",
    "Código Postal": "1806",
    "Teléfono": "4386-3694 / 0007",
    "maps_url": "https://maps.google.com/?cid=17626469416908567384",
    "rating": 4.5
  },
  {
    "Nombre": "Club Privado Loma Verde",
    "Dirección": "Ruta 9 Km 56,500",
    "Localidad": "Belen Escobar",
    "Código Postal": "1625",
    "Teléfono": "03488-493437/493624",
    "maps_url": "https://maps.google.com/?cid=3412795002078629196",
    "rating": 4.5
  },
  {
    "Nombre": "Club S. Y C. De Pato Gral. Balcarce",
    "Dirección": "Av. San Martin S/Nº",
    "Localidad": "Balcarce",
    "Código Postal": "7620",
    "Teléfono": "02266-423648/431199",
    "maps_url": "https://maps.google.com/?cid=17113739035104030730",
    "rating": 4.4
  },
  {
    "Nombre": "Club Sirio Libanes",
    "Dirección": "Av. Pellegrini S/Nº",
    "Localidad": "Pergamino",
    "Código Postal": "2700",
    "Teléfono": "02477-427439/423007",
    "maps_url": "https://maps.google.com/?cid=13994263082970705379",
    "rating": 4.5
  },
  {
    "Nombre": "Club Social Y Atletico La Pampa",
    "Dirección": "Ruta Nac. Nº 5 Km. 160",
    "Localidad": "Chivilcoy",
    "Código Postal": "6620",
    "Teléfono": "02346-427680",
    "maps_url": "https://maps.google.com/?cid=9891565195817282728",
    "rating": 4.3
  },
  {
    "Nombre": "Club Universitario Buenos Aires",
    "Dirección": "Ruta 8 Km 61,900",
    "Localidad": "Fatima",
    "Código Postal": "1633",
    "Teléfono": "02304 - 490269/490310",
    "maps_url": "https://maps.google.com/?cid=14248169645375475970",
    "rating": 4.4
  },
  {
    "Nombre": "Consorcio Country Mi Refugio",
    "Dirección": "Sargento Cabral S/Nº Esq. Lacarra",
    "Localidad": "Canning",
    "Código Postal": "1804",
    "Teléfono": "4295-8550",
    "maps_url": "https://maps.google.com/?cid=6918272020087596749",
    "rating": 4.3
  },
  {
    "Nombre": "Coronel Suarez Polo Club",
    "Dirección": "Seccion Quintas",
    "Localidad": "Coronel Suarez",
    "Código Postal": "7540",
    "Teléfono": "02926-422547 FAX 02926-422016",
    "maps_url": "https://maps.google.com/?cid=11977687537124547566",
    "rating": 4.5
  },
  {
    "Nombre": "Costa Esmeralda Golf Club",
    "Dirección": "Ruta Provincial 11 Km 380",
    "Localidad": "Pinamar",
    "Código Postal": "7167",
    "Teléfono": "(0800) 36 - 26782 int: 1106",
    "maps_url": "https://maps.google.com/?cid=7648040956186361044",
    "rating": 4.2
  },
  {
    "Nombre": "Country Club El Bosque",
    "Dirección": "Ruta 9 Km. 65.500",
    "Localidad": "Campana",
    "Código Postal": "2804",
    "Teléfono": "03489-447888/7/6",
    "maps_url": "https://maps.google.com/?cid=18291808249035195683",
    "rating": 4.5
  },
  {
    "Nombre": "Country Club El Pato",
    "Dirección": "Ruta 2 Km. 40,800",
    "Localidad": "El Pato",
    "Código Postal": "1893",
    "Teléfono": "02229-492112",
    "maps_url": "https://maps.google.com/?cid=10731849977560163003",
    "rating": 4.4
  },
  {
    "Nombre": "El Canton Golf",
    "Dirección": "Ruta 25 Y Calle Libertad",
    "Localidad": "Escobar",
    "Código Postal": "1625",
    "Teléfono": "",
    "maps_url": "https://maps.google.com/?cid=1765442992093815386",
    "rating": 4.6
  },
  {
    "Nombre": "El Nacional Club De Campo",
    "Dirección": "Av. Corrientes Y Ruta 24",
    "Localidad": "General Rodriguez",
    "Código Postal": "1748",
    "Teléfono": "0237 4287450",
    "maps_url": "https://maps.google.com/?cid=1977028706135825758",
    "rating": 4.5
  },
  {
    "Nombre": "El Paraiso Country Club",
    "Dirección": "Av. 33 Y Calle 21",
    "Localidad": "Guernica",
    "Código Postal": "1862",
    "Teléfono": "02224-471432",
    "maps_url": "https://maps.google.com/?cid=2781427935988206875",
    "rating": 4.3
  },
  {
    "Nombre": "El Sosiego Country Club",
    "Dirección": "Sargento Cabral 4581",
    "Localidad": "Canning",
    "Código Postal": "1804",
    "Teléfono": "4295-8280/8288",
    "maps_url": "https://maps.google.com/?cid=1610220497981806132",
    "rating": 4.4
  },
  {
    "Nombre": "El Valle De Tandil Golf Club",
    "Dirección": "Av. Don Bosco Y Ceferino Namuncura",
    "Localidad": "Tandil",
    "Código Postal": "7000",
    "Teléfono": "02293-445873",
    "maps_url": "https://maps.google.com/?cid=5167152870963188004",
    "rating": 4.6
  },
  {
    "Nombre": "El Venado Country Club",
    "Dirección": "Srgto. Cabral Y Escr. Vazquez S/N",
    "Localidad": "Canning",
    "Código Postal": "1804",
    "Teléfono": "4295-8413/9210/8713",
    "maps_url": "https://maps.google.com/?cid=389617146367492129",
    "rating": 4.3
  },
  {
    "Nombre": "El Venado Country Club Ii",
    "Dirección": "Escribano 3550",
    "Localidad": "Canning",
    "Código Postal": "1842",
    "Teléfono": "4295-8608",
    "maps_url": "https://maps.google.com/?cid=389617146367492129",
    "rating": 4.3
  },
  {
    "Nombre": "Esperanza Golf Club",
    "Dirección": "Sargento Cabral 2191",
    "Localidad": "Canning",
    "Código Postal": "1842",
    "Teléfono": "4295-8450   FAX 4295-8665",
    "maps_url": "https://maps.google.com/?cid=6145983474131748628",
    "rating": 4.1
  },
  {
    "Nombre": "Estancia Benquerencia Farm Club",
    "Dirección": "Ruta 41 S/N",
    "Localidad": "San Miguel Del Monte",
    "Código Postal": "7220",
    "Teléfono": "02227-15614315",
    "maps_url": "https://maps.google.com/?cid=6351728150502512906",
    "rating": 4.8
  },
  {
    "Nombre": "Estancia Villa Maria Golf Club",
    "Dirección": "Av. Pereda 200",
    "Localidad": "Maximo Paz",
    "Código Postal": "1812",
    "Teléfono": "4815-0989",
    "maps_url": "https://maps.google.com/?cid=14706002351286836837",
    "rating": 4.6
  },
  {
    "Nombre": "Estancias Golf Club",
    "Dirección": "Ruta Panamericana Km. 56,5",
    "Localidad": "Pilar",
    "Código Postal": "1630",
    "Teléfono": "011 63850699",
    "maps_url": "https://maps.google.com/?cid=17150054499516078511",
    "rating": 4.5
  },
  {
    "Nombre": "Everlinks Club De Golf",
    "Dirección": "Beschedt 4200",
    "Localidad": "Lujan",
    "Código Postal": "6700",
    "Teléfono": "",
    "maps_url": "https://maps.google.com/?cid=809694541155878435",
    "rating": 4.6
  },
  {
    "Nombre": "Fincas De San Vicente Club De Campo S. A.",
    "Dirección": "Juan Pablo Ii 1600",
    "Localidad": "San Vicente",
    "Código Postal": "1865",
    "Teléfono": "",
    "maps_url": "https://maps.google.com/?cid=14343460780749732452",
    "rating": 4.5
  },
  {
    "Nombre": "Golf Chascomus Country Club",
    "Dirección": "Juan Manuel De Rosas 2250 Y Ruta Pcial 20",
    "Localidad": "Chascomus",
    "Código Postal": "7130",
    "Teléfono": "02241-420085 FAX 02241-420085",
    "maps_url": "https://maps.google.com/?q=Golf+Chascomus+Country+Club&ftid=0x95980cd75966f34d:0x2b744e748af16656",
    "rating": ""
  },
  {
    "Nombre": "Golf Club Argentino",
    "Dirección": "Ruta 8 Km. 41,500",
    "Localidad": "Jose C. Paz",
    "Código Postal": "1665",
    "Teléfono": "02320-491190/492218",
    "maps_url": "https://maps.google.com/?cid=5689868341668168197",
    "rating": 4.5
  },
  {
    "Nombre": "Golf Club Azul",
    "Dirección": "Ruta Nac. Nº 3 Km. 298",
    "Localidad": "Azul",
    "Código Postal": "7300",
    "Teléfono": "02281-433400 FAX 02281-430999",
    "maps_url": "https://maps.google.com/?cid=18446039031238531155",
    "rating": 4.5
  },
  {
    "Nombre": "Golf Club Carhue",
    "Dirección": "Acceso Ruta 33 Y Rivadavia",
    "Localidad": "Carhue",
    "Código Postal": "6430",
    "Teléfono": "02923-15643201 y 02936-432703",
    "maps_url": "https://maps.google.com/?cid=16898257700550015132",
    "rating": 4.7
  },
  {
    "Nombre": "Golf Club Dolores",
    "Dirección": "Chascomus  173",
    "Localidad": "Dolores",
    "Código Postal": "7100",
    "Teléfono": "02245-446681/446904/447783",
    "maps_url": "https://maps.google.com/?cid=8606167542054297716",
    "rating": 4.7
  },
  {
    "Nombre": "Golf Club Gral. San Martin",
    "Dirección": "Lope De Vega",
    "Localidad": "Villa Raffo",
    "Código Postal": "1674",
    "Teléfono": "011 4757-1600",
    "maps_url": "https://maps.google.com/?cid=8225870759431868539",
    "rating": 4.4
  },
  {
    "Nombre": "Golf Club Mercedes",
    "Dirección": "Ruta Nac. Nº 5 Km. 104,5",
    "Localidad": "Mercedes",
    "Código Postal": "6600",
    "Teléfono": "02324-427515/434723",
    "maps_url": "https://maps.google.com/?cid=18124699113105803950",
    "rating": 5
  },
  {
    "Nombre": "Golf Club Monte Hermoso",
    "Dirección": "Monte Hermoso Golf Club",
    "Localidad": "Monte Hermoso Este",
    "Código Postal": "8153",
    "Teléfono": "02921-482888",
    "maps_url": "https://maps.google.com/?cid=17609029174370781775",
    "rating": 4.5
  },
  {
    "Nombre": "Golf Club Pehuajo",
    "Dirección": "Ruta 5 Acc. Al Aeródromo Km. 365",
    "Localidad": "Pehuajo",
    "Código Postal": "6450",
    "Teléfono": "02396-15613374/472309",
    "maps_url": "https://maps.google.com/?cid=10475358230107049736",
    "rating": 4.4
  },
  {
    "Nombre": "Golf Club Puerto Belgrano",
    "Dirección": "Base Naval Puerto Belgrano",
    "Localidad": "Puerto Belgrano",
    "Código Postal": "8111",
    "Teléfono": "02932-487479",
    "maps_url": "https://maps.google.com/?cid=14933812659879308370",
    "rating": 4.6
  },
  {
    "Nombre": "Golf Club Sierra De La Ventana",
    "Dirección": "Av. Del Golf Nº 300",
    "Localidad": "Sierra De La Ventana",
    "Código Postal": "8168",
    "Teléfono": "0291-4915113 FAX0291-4915303",
    "maps_url": "https://maps.google.com/?cid=6399249046979514484",
    "rating": 4.6
  },
  {
    "Nombre": "Golf Club Tapalque",
    "Dirección": "Ruta 51 Km. 268",
    "Localidad": "Tapalque",
    "Código Postal": "7303",
    "Teléfono": "02283-420344/420879/420368/420130",
    "maps_url": "",
    "rating": ""
  },
  {
    "Nombre": "Golf San Sebastian",
    "Dirección": "Agustin Garcia 9501",
    "Localidad": "Benavidez",
    "Código Postal": "1621",
    "Teléfono": "",
    "maps_url": "",
    "rating": ""
  },
  {
    "Nombre": "Golfer'S Country Club",
    "Dirección": "Ruta 28 Km. 4,500",
    "Localidad": "Pilar",
    "Código Postal": "1629",
    "Teléfono": "02304- 401364/9 FAX 02322-401372",
    "maps_url": "https://maps.google.com/?cid=2807693947196676846",
    "rating": 4.5
  },
  {
    "Nombre": "Good Year Golf Club",
    "Dirección": "Manuel Ocampo Esquina Gaboto",
    "Localidad": "Hurlingham",
    "Código Postal": "1686",
    "Teléfono": "",
    "maps_url": "https://maps.google.com/?cid=4780036723252977929",
    "rating": 4.2
  },
  {
    "Nombre": "Haras Del Sur Ii C. Campo",
    "Dirección": "Ruta 2 Km. 73",
    "Localidad": "Brandsen",
    "Código Postal": "1980",
    "Teléfono": "",
    "maps_url": "",
    "rating": ""
  },
  {
    "Nombre": "Haras Del Sur Iii Club De Campo",
    "Dirección": "Ruta 2 Km 70",
    "Localidad": "La Plata",
    "Código Postal": "null",
    "Teléfono": "1156555926",
    "maps_url": "",
    "rating": ""
  },
  {
    "Nombre": "Haras Santa Maria",
    "Dirección": "Los Cerros Y Oldman 704 - Loma Verde",
    "Localidad": "Escobar",
    "Código Postal": "1625",
    "Teléfono": "034888 - 493665",
    "maps_url": "https://maps.google.com/?cid=7513961922124312944",
    "rating": 4.5
  },
  {
    "Nombre": "Highland Park Country Club",
    "Dirección": "Av Los Jazmines Y Las Campanillas",
    "Localidad": "Del Viso",
    "Código Postal": "1669",
    "Teléfono": "02320 - 470090",
    "maps_url": "https://maps.google.com/?cid=15702102707808793149",
    "rating": 4.4
  },
  {
    "Nombre": "Hindu Club",
    "Dirección": "Ruta 202 Y Arricau S/Nº",
    "Localidad": "Don Torcuato",
    "Código Postal": "1611",
    "Teléfono": "4741-6150/57",
    "maps_url": "https://maps.google.com/?cid=5955472914636309960",
    "rating": 4.4
  },
  {
    "Nombre": "Indio Cua Country Club",
    "Dirección": "Ruta 6 Km. 173",
    "Localidad": "Capilla Del Señor",
    "Código Postal": "2812",
    "Teléfono": "02323-470033",
    "maps_url": "",
    "rating": ""
  },
  {
    "Nombre": "Ituzaingo Golf Club",
    "Dirección": "Vicente Gerde 97",
    "Localidad": "San Antonio De Padua",
    "Código Postal": "1718",
    "Teléfono": "0220-4822331/4826398",
    "maps_url": "https://maps.google.com/?cid=7387002978000592411",
    "rating": 4.3
  },
  {
    "Nombre": "Jockey Club Argentino",
    "Dirección": "Av. Marquez 1700",
    "Localidad": "San Isidro",
    "Código Postal": "1642",
    "Teléfono": "4743-1001/4/1678 Dto.Pablo 4723-5596",
    "maps_url": "https://maps.google.com/?cid=18083805568167420133",
    "rating": 4.6
  },
  {
    "Nombre": "Junin Golf Cub",
    "Dirección": "Ruta Nac. Nº 7 Km. 257,5",
    "Localidad": "Junin",
    "Código Postal": "6000",
    "Teléfono": "02362-427561/446800",
    "maps_url": "https://maps.google.com/?cid=10991474725270844515",
    "rating": 4.4
  },
  {
    "Nombre": "La Colina Golf Club",
    "Dirección": "Ruta 6 Rio Luan Open Door",
    "Localidad": "Lujan",
    "Código Postal": "6708",
    "Teléfono": "02323 - 439017",
    "maps_url": "https://maps.google.com/?cid=14286183729112110172",
    "rating": 4.5
  },
  {
    "Nombre": "La Lucila Polo Club",
    "Dirección": "Ithurbide S/N Seccion Quinta",
    "Localidad": "General Villegas",
    "Código Postal": "6230",
    "Teléfono": "03388-422042",
    "maps_url": "https://maps.google.com/?cid=16858970815434586018",
    "rating": 4.6
  },
  {
    "Nombre": "La Madrid Golf Club",
    "Dirección": "Ruta  86",
    "Localidad": "General La Madrid",
    "Código Postal": "7406",
    "Teléfono": "NO POSEE",
    "maps_url": "https://maps.google.com/?cid=3137102270875439482",
    "rating": 4.2
  },
  {
    "Nombre": "La Providencia Resort",
    "Dirección": "Ruta 52. Km 1,5",
    "Localidad": "Canning",
    "Código Postal": "1807",
    "Teléfono": "",
    "maps_url": "",
    "rating": ""
  },
  {
    "Nombre": "La Reserva Cardales Resort Country Club",
    "Dirección": "Ruta 9 Km. 61",
    "Localidad": "Campana",
    "Código Postal": "2804",
    "Teléfono": "03489 - 466004 / 6",
    "maps_url": "",
    "rating": ""
  },
  {
    "Nombre": "Laprida Golf Club",
    "Dirección": "Alsina 1454",
    "Localidad": "Laprida",
    "Código Postal": "7414",
    "Teléfono": "02285 - 420105 / 420532",
    "maps_url": "https://maps.google.com/?cid=6607876942907022847",
    "rating": 5
  },
  {
    "Nombre": "Larena Country Club",
    "Dirección": "Ruta Prov. 6 Km 176",
    "Localidad": "Pilar",
    "Código Postal": "1629",
    "Teléfono": "02304-490248/302 4394-9871 FAX490249",
    "maps_url": "https://maps.google.com/?cid=1774455988613501196",
    "rating": 4.5
  },
  {
    "Nombre": "Las Cañuelas Club De Campo",
    "Dirección": "Ruta Nac. N° 3 Km. 56,300",
    "Localidad": "Cañuelas",
    "Código Postal": "1814",
    "Teléfono": "4729 - 8921 / 8980 / 1800",
    "maps_url": "https://maps.google.com/?cid=1813195820438542730",
    "rating": 4.5
  },
  {
    "Nombre": "Las Lajas Country Club",
    "Dirección": "Acceso Oeste Km. 50,500",
    "Localidad": "General Rodriguez",
    "Código Postal": "1748",
    "Teléfono": "0237-4852900 FAX 4852900/901",
    "maps_url": "https://maps.google.com/?cid=9843238415377501281",
    "rating": 4.4
  },
  {
    "Nombre": "Las Mulitas Golf Club",
    "Dirección": "Calles 25 Y 204",
    "Localidad": "25 De Mayo",
    "Código Postal": "6660",
    "Teléfono": "",
    "maps_url": "https://maps.google.com/?cid=3414950471910820230",
    "rating": 4.7
  },
  {
    "Nombre": "Lincoln Golf Club",
    "Dirección": "Parque Municipal Gral.S. Martin Esquina Sur",
    "Localidad": "Lincoln",
    "Código Postal": "6070",
    "Teléfono": "02355-422342/422118/422365",
    "maps_url": "https://maps.google.com/?cid=14805689542195975724",
    "rating": 4.4
  },
  {
    "Nombre": "Links Pinamar S.A.",
    "Dirección": "Av Shaw 1640 Y Goleta Independencia",
    "Localidad": "Pinamar",
    "Código Postal": "7167",
    "Teléfono": "02254 - 491815 / 491810",
    "maps_url": "https://maps.google.com/?cid=8045995816764518257",
    "rating": 4.5
  },
  {
    "Nombre": "Los Cardales Country Club",
    "Dirección": "Ruta 4 Km. 4",
    "Localidad": "Los Cardales",
    "Código Postal": "2814",
    "Teléfono": "02322-525000 INT. 14",
    "maps_url": "",
    "rating": ""
  },
  {
    "Nombre": "Los Lagartos Country Club",
    "Dirección": "Ruta Panam. Km 45,500 Acc. Norte",
    "Localidad": "Pilar",
    "Código Postal": "1629",
    "Teléfono": "02304 - 666308/668309",
    "maps_url": "https://maps.google.com/?cid=1611750009001306033",
    "rating": 4.4
  },
  {
    "Nombre": "Mapuche Country Club",
    "Dirección": "Panamericana (Ramal Pilar) Km. 48,500",
    "Localidad": "Pilar",
    "Código Postal": "1629",
    "Teléfono": "02304-472805",
    "maps_url": "https://maps.google.com/?cid=12251781125237023390",
    "rating": 4.4
  },
  {
    "Nombre": "Mar Del Plata Golf Club",
    "Dirección": "Aristobulo Del Valle 3940",
    "Localidad": "Mar Del Plata",
    "Código Postal": "7600",
    "Teléfono": "0223-4862323 / 4862329 / 4862221",
    "maps_url": "https://maps.google.com/?cid=11661970238255083556",
    "rating": 4.4
  },
  {
    "Nombre": "Marayui Country Club",
    "Dirección": "Playa Chapadmalal",
    "Localidad": "Chapadmalal",
    "Código Postal": "7605",
    "Teléfono": "0223-4605152 FAX 0223-4605222",
    "maps_url": "https://maps.google.com/?cid=2305386421560676515",
    "rating": 4.6
  },
  {
    "Nombre": "Marinas Golf",
    "Dirección": "Canal Aliviador Y Ruta 27",
    "Localidad": "Tigre",
    "Código Postal": "1648",
    "Teléfono": "5032-8317/8316",
    "maps_url": "https://maps.google.com/?cid=15663135156811458637",
    "rating": 4.5
  },
  {
    "Nombre": "Martindale Country Club",
    "Dirección": "Av. Juan Domingo Peron 2375",
    "Localidad": "Pilar",
    "Código Postal": "1629",
    "Teléfono": "02304-406700",
    "maps_url": "https://maps.google.com/?cid=15853012450356656752",
    "rating": 4.5
  },
  {
    "Nombre": "Maschwitz Club",
    "Dirección": "Ruta 9 Km. 45",
    "Localidad": "Ingeniero Maschwitz",
    "Código Postal": "1623",
    "Teléfono": "0348-441587/4440074",
    "maps_url": "",
    "rating": ""
  },
  {
    "Nombre": "Mayling Club De Campo",
    "Dirección": "Ruta Panam. Km. 50 Ramal A Pilar",
    "Localidad": "Pilar",
    "Código Postal": "1629",
    "Teléfono": "02304-494016   02304-494469",
    "maps_url": "https://maps.google.com/?cid=14321078339695665046",
    "rating": 4.5
  },
  {
    "Nombre": "Medal Country Club Pilar",
    "Dirección": "Ruta 34 Km. 10",
    "Localidad": "Pilar",
    "Código Postal": "1629",
    "Teléfono": "",
    "maps_url": "",
    "rating": ""
  },
  {
    "Nombre": "Media Luna Polo Club",
    "Dirección": "Ameghino",
    "Localidad": "Ameghino",
    "Código Postal": "6064",
    "Teléfono": "",
    "maps_url": "https://maps.google.com/?cid=16458345596822134416",
    "rating": 4.7
  },
  {
    "Nombre": "Miraflores Country Club",
    "Dirección": "Ruta Panam. Km. 35,5 Ramal A Pilar",
    "Localidad": "Garin",
    "Código Postal": "1619",
    "Teléfono": "03327-454801 / 454975",
    "maps_url": "https://maps.google.com/?cid=14250220067898730408",
    "rating": 4.3
  },
  {
    "Nombre": "Miralagos C. Campo",
    "Dirección": "Ruta 2 Km. 65,0",
    "Localidad": "La Plata",
    "Código Postal": "1900",
    "Teléfono": "",
    "maps_url": "",
    "rating": ""
  },
  {
    "Nombre": "Miramar Links",
    "Dirección": "Ruta Provincial 11 Km. 4,5",
    "Localidad": "Miramar",
    "Código Postal": "7607",
    "Teléfono": "02291-422244/433001",
    "maps_url": "",
    "rating": ""
  },
  {
    "Nombre": "Namuncura Polo Club",
    "Dirección": "Seccion Quintas",
    "Localidad": "America",
    "Código Postal": "6237",
    "Teléfono": "02337 - 452586",
    "maps_url": "",
    "rating": ""
  },
  {
    "Nombre": "Nautico Escobar Country Club",
    "Dirección": "Av. Kenneddy S/Nº",
    "Localidad": "El Cazador Escobar",
    "Código Postal": "1625",
    "Teléfono": "03488-487840/480932/487166",
    "maps_url": "https://maps.google.com/?cid=10082274968296312687",
    "rating": 4.5
  },
  {
    "Nombre": "Navarro Golf Club",
    "Dirección": "Acceso Ruta 41",
    "Localidad": "Navarro",
    "Código Postal": "6605",
    "Teléfono": "02272-430627",
    "maps_url": "https://maps.google.com/?cid=17566717882254098625",
    "rating": 4.7
  },
  {
    "Nombre": "Necochea Golf Club",
    "Dirección": "Avenida Armada Argentina S/Nº",
    "Localidad": "Quequen",
    "Código Postal": "7631",
    "Teléfono": "02262-451532/450684",
    "maps_url": "https://maps.google.com/?cid=12768596509326941945",
    "rating": 4.7
  },
  {
    "Nombre": "Nordelta Golf Club",
    "Dirección": "Av. Del Golf 1780",
    "Localidad": "Tigre",
    "Código Postal": "1670",
    "Teléfono": "4871-3103",
    "maps_url": "https://maps.google.com/?cid=11593007919817389109",
    "rating": 4.6
  },
  {
    "Nombre": "North Beach Links",
    "Dirección": "Ruta 11 Km 378",
    "Localidad": "Buenos Aires",
    "Código Postal": "null",
    "Teléfono": "",
    "maps_url": "",
    "rating": ""
  },
  {
    "Nombre": "Ocaragua Golf Club",
    "Dirección": "Ruta 3 Km 50",
    "Localidad": "Marcos Paz",
    "Código Postal": "1717",
    "Teléfono": "0237 - 4686152",
    "maps_url": "",
    "rating": ""
  },
  {
    "Nombre": "Olivos Golf Club",
    "Dirección": "Ruta Panam. Km. 32,400 Ramal Pilar",
    "Localidad": "Los Polvorines",
    "Código Postal": "1613",
    "Teléfono": "4587-1076/0035/0686/1132/1288",
    "maps_url": "https://maps.google.com/?cid=3500851402863582092",
    "rating": 4.5
  },
  {
    "Nombre": "Org. Hebrea Argentina (Macabi)",
    "Dirección": "Defensa Y Sargento Cabral",
    "Localidad": "Bº Mitre (San Miguel)",
    "Código Postal": "1663",
    "Teléfono": "4455-7000",
    "maps_url": "https://maps.google.com/?cid=14777288695680690887",
    "rating": 4.3
  },
  {
    "Nombre": "Pacheco Golf Club",
    "Dirección": "Autovia Bancalari Nordelta Km 1",
    "Localidad": "General Pacheco",
    "Código Postal": "1617",
    "Teléfono": "4740-9820/8479 4726-1708",
    "maps_url": "",
    "rating": ""
  },
  {
    "Nombre": "Pago Chico Country Club",
    "Dirección": "Ruta 229 Km. 16",
    "Localidad": "Punta Alta",
    "Código Postal": "8109",
    "Teléfono": "0291 - 4553595",
    "maps_url": "",
    "rating": ""
  },
  {
    "Nombre": "Pihue Golf",
    "Dirección": "Ruta 33 Km128,5",
    "Localidad": "Pigüe",
    "Código Postal": "8170",
    "Teléfono": "0923-475813",
    "maps_url": "",
    "rating": ""
  },
  {
    "Nombre": "Pilar Del Lago",
    "Dirección": "Av.Centenario Y Amancio Alcorta",
    "Localidad": "Pilar",
    "Código Postal": "1633",
    "Teléfono": "02304-480418/480419",
    "maps_url": "https://maps.google.com/?cid=18326949235232633580",
    "rating": 4.5
  },
  {
    "Nombre": "Pilar Golf Club",
    "Dirección": "Ruta 8 Km. 60,500",
    "Localidad": "Pilar",
    "Código Postal": "1633",
    "Teléfono": "02304-490880/8",
    "maps_url": "https://maps.google.com/?cid=14183684583043447059",
    "rating": 4.7
  },
  {
    "Nombre": "Pilara Golf",
    "Dirección": "Panamericana Ramal Pilar Km. 56,500",
    "Localidad": "Pilar",
    "Código Postal": "1629",
    "Teléfono": "02304 - 441207",
    "maps_url": "https://maps.google.com/?cid=3955326060379712929",
    "rating": 4.4
  },
  {
    "Nombre": "Puan Golf",
    "Dirección": "Seccion Chacras",
    "Localidad": "Puan",
    "Código Postal": "8180",
    "Teléfono": "02923-498024 FAX 02923-498754",
    "maps_url": "https://maps.google.com/?cid=6980122007329357521",
    "rating": 4.8
  },
  {
    "Nombre": "Ranelagh Golf Club",
    "Dirección": "Av. Este 901 Y Calle 359",
    "Localidad": "Ranelagh",
    "Código Postal": "1886",
    "Teléfono": "4258-8514/3563",
    "maps_url": "https://maps.google.com/?cid=18198575870066310108",
    "rating": 4.6
  },
  {
    "Nombre": "Saladillo Golf Club",
    "Dirección": "Moreno Y Rivadavia",
    "Localidad": "Saladillo",
    "Código Postal": "7260",
    "Teléfono": "02345-15-655679",
    "maps_url": "https://maps.google.com/?cid=1926634823496163042",
    "rating": 4.8
  },
  {
    "Nombre": "San Andres Golf Club",
    "Dirección": "Dr. Francisco Aleu 500",
    "Localidad": "San Andres",
    "Código Postal": "1651",
    "Teléfono": "4752-3994 4755-7097 4753-1931",
    "maps_url": "https://maps.google.com/?cid=18372411555725070194",
    "rating": 4.6
  },
  {
    "Nombre": "San Diego Country Club",
    "Dirección": "Acc. Oeste Km 42 , Francisco Alvarez",
    "Localidad": "Moreno",
    "Código Postal": "1744",
    "Teléfono": "0237-4832209",
    "maps_url": "https://maps.google.com/?cid=15213259362814612687",
    "rating": 4.4
  },
  {
    "Nombre": "San Eliseo Golf & Country Club",
    "Dirección": "Ruta 58 Km 18",
    "Localidad": "Presidente Perón",
    "Código Postal": "1865",
    "Teléfono": "02225 - 480034 / 482848  4803-5881",
    "maps_url": "",
    "rating": ""
  },
  {
    "Nombre": "San Isidro Golf Club",
    "Dirección": "Av. Juan Segundo Fernandez 386",
    "Localidad": "San Isidro",
    "Código Postal": "1642",
    "Teléfono": "4766-6625/0750 FAX 4765 - 2532",
    "maps_url": "https://maps.google.com/?cid=12489548595704444177",
    "rating": 4.4
  },
  {
    "Nombre": "San Jorge Golf Club",
    "Dirección": "Combate De Pavon 2201",
    "Localidad": "Hurlingham",
    "Código Postal": "1686",
    "Teléfono": "4452-7676",
    "maps_url": "https://maps.google.com/?cid=9890574834015432766",
    "rating": 4.4
  },
  {
    "Nombre": "San Miguel De Ghiso Country Club",
    "Dirección": "Santa Fe 2888",
    "Localidad": "Bella Vista",
    "Código Postal": "1661",
    "Teléfono": "4666-7027/8289",
    "maps_url": "https://maps.google.com/?cid=1880817531964491206",
    "rating": 4.3
  },
  {
    "Nombre": "San Nicolas Golf Club",
    "Dirección": "Av. Savio Y Ruta Prov. Nº 1001",
    "Localidad": "San Nicolas",
    "Código Postal": "2900",
    "Teléfono": "03461-462219/462222",
    "maps_url": "https://maps.google.com/?cid=10812480523280826005",
    "rating": 4.4
  },
  {
    "Nombre": "San Patricio Golf",
    "Dirección": "Ezeiza 145 Esquina Pringles",
    "Localidad": "General Pacheco",
    "Código Postal": "1617",
    "Teléfono": "4715-1456/7",
    "maps_url": "",
    "rating": ""
  },
  {
    "Nombre": "San Pedro Golf Club",
    "Dirección": "Ruta 9 Km 161,5",
    "Localidad": "San Pedro",
    "Código Postal": "2930",
    "Teléfono": "011 15-4448-0906",
    "maps_url": "https://maps.google.com/?cid=14029714493228519127",
    "rating": 4.4
  },
  {
    "Nombre": "Santa Margarita Golf Club",
    "Dirección": "Ruta 8 Km. 153,5",
    "Localidad": "Capitan Sarmiento",
    "Código Postal": "2752",
    "Teléfono": "0247-8482871 en BsAs. 011 4811-2976",
    "maps_url": "",
    "rating": ""
  },
  {
    "Nombre": "Santa Teresita Golf Club",
    "Dirección": "Santa Teresita El Monte",
    "Localidad": "Santa Teresita",
    "Código Postal": "7107",
    "Teléfono": "02246-430014",
    "maps_url": "https://maps.google.com/?cid=4605805492788022943",
    "rating": 4.5
  },
  {
    "Nombre": "Scholem Aleijem Bialik",
    "Dirección": "Blas Parera 1300",
    "Localidad": "Tristan Suarez",
    "Código Postal": "1806",
    "Teléfono": "4234-8261/8416",
    "maps_url": "",
    "rating": ""
  },
  {
    "Nombre": "Sierra De Los Padres Golf Club",
    "Dirección": "Calle Lorenzo Y Luis S/N",
    "Localidad": "Sierra De Los Padres",
    "Código Postal": "7601",
    "Teléfono": "0223-4630062",
    "maps_url": "https://maps.google.com/?cid=7273398021995444001",
    "rating": 4.5
  },
  {
    "Nombre": "Smithfield Golf Club",
    "Dirección": "Ruta 12 Km. 84",
    "Localidad": "Zarate",
    "Código Postal": "2800",
    "Teléfono": "03487-421835",
    "maps_url": "",
    "rating": ""
  },
  {
    "Nombre": "Sociedad Hebraica Argentina",
    "Dirección": "Ruta Nac. Nº 8 Km. 51,500",
    "Localidad": "Pilar",
    "Código Postal": "1629",
    "Teléfono": "02304 - 652718/9",
    "maps_url": "https://maps.google.com/?cid=7000551989397739253",
    "rating": 4.3
  },
  {
    "Nombre": "St. Thomas Sur Country Club",
    "Dirección": "Ruta 52 Km 3,500",
    "Localidad": "Canning",
    "Código Postal": "1807",
    "Teléfono": "4295 - 7582/ 7583 /7367",
    "maps_url": "https://maps.google.com/?cid=15481639464762879635",
    "rating": 4.5
  },
  {
    "Nombre": "Tandil Golf Club",
    "Dirección": "Acceso Ruta 226 Y Calle Colombia",
    "Localidad": "Tandil",
    "Código Postal": "7000",
    "Teléfono": "0249-4406976",
    "maps_url": "https://maps.google.com/?cid=1175620939659717726",
    "rating": 4.6
  },
  {
    "Nombre": "Tortugas Country Club",
    "Dirección": "Au Panam. Km 37,500 Acc. A Pilar",
    "Localidad": "Tortuguitas",
    "Código Postal": "1667",
    "Teléfono": "02320-558411/491262 FAX 02320-496352",
    "maps_url": "https://maps.google.com/?cid=376295407873358621",
    "rating": 4.4
  },
  {
    "Nombre": "Trenque Lauquen Polo Club",
    "Dirección": "Avenida 25 De Mayo S/N (Prolongación)",
    "Localidad": "Trenque Lauquen",
    "Código Postal": "6400",
    "Teléfono": "02392-423555",
    "maps_url": "https://maps.google.com/?cid=7946420159323507335",
    "rating": 4.6
  },
  {
    "Nombre": "Tres Arroyos Golf Club",
    "Dirección": "Juan B. Justo 200",
    "Localidad": "Tres Arroyos",
    "Código Postal": "7500",
    "Teléfono": "02983-432202",
    "maps_url": "https://maps.google.com/?cid=12905338016399033097",
    "rating": 4.5
  },
  {
    "Nombre": "Upcn Golf",
    "Dirección": "Calle 89 Y 142, Arana",
    "Localidad": "La Plata",
    "Código Postal": "1900",
    "Teléfono": "",
    "maps_url": "https://maps.google.com/?cid=3852349967671820990",
    "rating": 4.3
  },
  {
    "Nombre": "Villa Gesell Golf Club",
    "Dirección": "Camino De Los Pioneros 2463",
    "Localidad": "Villa Gesell",
    "Código Postal": "7165",
    "Teléfono": "02255-458249",
    "maps_url": "https://maps.google.com/?cid=925097382704481589",
    "rating": 4.5
  },
  {
    "Nombre": "Village Golf And Tennis Club",
    "Dirección": "Hipolito Yrigoyen 1754",
    "Localidad": "Tortuguitas",
    "Código Postal": "1667",
    "Teléfono": "02320 - 401026",
    "maps_url": "https://maps.google.com/?cid=5618756316308483580",
    "rating": 4.4
  },
  {
    "Nombre": "Zen Golf  Spa",
    "Dirección": "Martin Fierro Y Juana De Arco",
    "Localidad": "Canning",
    "Código Postal": "1807",
    "Teléfono": "",
    "maps_url": "https://maps.google.com/?cid=17166015114698834557",
    "rating": 4.1
  }
]

